odoo/addons/dead_mans_switch_client/README.rst
odoo/addons/dead_mans_switch_client/__init__.py
odoo/addons/dead_mans_switch_client/__manifest__.py
odoo/addons/dead_mans_switch_client/data/ir_actions.xml
odoo/addons/dead_mans_switch_client/data/ir_cron.xml
odoo/addons/dead_mans_switch_client/demo/dead_mans_switch_client_demo.yml
odoo/addons/dead_mans_switch_client/i18n/am.po
odoo/addons/dead_mans_switch_client/i18n/ar.po
odoo/addons/dead_mans_switch_client/i18n/bg.po
odoo/addons/dead_mans_switch_client/i18n/bs.po
odoo/addons/dead_mans_switch_client/i18n/ca.po
odoo/addons/dead_mans_switch_client/i18n/cs.po
odoo/addons/dead_mans_switch_client/i18n/da.po
odoo/addons/dead_mans_switch_client/i18n/de.po
odoo/addons/dead_mans_switch_client/i18n/el_GR.po
odoo/addons/dead_mans_switch_client/i18n/en_GB.po
odoo/addons/dead_mans_switch_client/i18n/es.po
odoo/addons/dead_mans_switch_client/i18n/es_AR.po
odoo/addons/dead_mans_switch_client/i18n/es_CL.po
odoo/addons/dead_mans_switch_client/i18n/es_CO.po
odoo/addons/dead_mans_switch_client/i18n/es_CR.po
odoo/addons/dead_mans_switch_client/i18n/es_DO.po
odoo/addons/dead_mans_switch_client/i18n/es_EC.po
odoo/addons/dead_mans_switch_client/i18n/es_ES.po
odoo/addons/dead_mans_switch_client/i18n/es_MX.po
odoo/addons/dead_mans_switch_client/i18n/es_PE.po
odoo/addons/dead_mans_switch_client/i18n/es_PY.po
odoo/addons/dead_mans_switch_client/i18n/es_VE.po
odoo/addons/dead_mans_switch_client/i18n/et.po
odoo/addons/dead_mans_switch_client/i18n/eu.po
odoo/addons/dead_mans_switch_client/i18n/fa.po
odoo/addons/dead_mans_switch_client/i18n/fi.po
odoo/addons/dead_mans_switch_client/i18n/fr.po
odoo/addons/dead_mans_switch_client/i18n/fr_CA.po
odoo/addons/dead_mans_switch_client/i18n/fr_CH.po
odoo/addons/dead_mans_switch_client/i18n/gl.po
odoo/addons/dead_mans_switch_client/i18n/gl_ES.po
odoo/addons/dead_mans_switch_client/i18n/he.po
odoo/addons/dead_mans_switch_client/i18n/hr.po
odoo11_addon_dead_mans_switch_client-11.0.1.0.0.dist-info/METADATA
odoo11_addon_dead_mans_switch_client-11.0.1.0.0.dist-info/RECORD
odoo11_addon_dead_mans_switch_client-11.0.1.0.0.dist-info/WHEEL
odoo11_addon_dead_mans_switch_client-11.0.1.0.0.dist-info/top_level.txt
